sentry_oss_nodestore/__init__.py
sentry_oss_nodestore/backend.py
sentry_oss_nodestore-0.0.4.dist-info/LICENSE
sentry_oss_nodestore-0.0.4.dist-info/METADATA
sentry_oss_nodestore-0.0.4.dist-info/WHEEL
sentry_oss_nodestore-0.0.4.dist-info/top_level.txt
sentry_oss_nodestore-0.0.4.dist-info/RECORD
