Metadata-Version: 2.1
Name: sentry-oss-nodestore
Version: 0.0.4
Summary: sentry oss node store
Home-page: UNKNOWN
Author: yuanxiao
Author-email: yuan6785@163.com
License: UNKNOWN
Platform: UNKNOWN
Classifier: Programming Language :: Python :: 3
Classifier: License :: OSI Approved :: MIT License
Classifier: Operating System :: OS Independent
Requires-Python: >=3.5
Requires-Dist: oss2 (==2.14.0)
